ENGR131_2024/__init__.py
ENGR131_2024-0.0.2.dist-info/LICENSE
ENGR131_2024-0.0.2.dist-info/METADATA
ENGR131_2024-0.0.2.dist-info/WHEEL
ENGR131_2024-0.0.2.dist-info/top_level.txt
ENGR131_2024-0.0.2.dist-info/RECORD
