Metadata-Version: 2.1
Name: ENGR131-2024
Version: 0.0.2
Summary: ENGR131_2024 package
Author: Joshua C. Agar
License-File: LICENSE
Requires-Dist: accessible-pygments ==0.0.4
Requires-Dist: alabaster ==0.7.13
Requires-Dist: anyio ==4.2.0
Requires-Dist: argon2-cffi ==23.1.0
Requires-Dist: argon2-cffi-bindings ==21.2.0
Requires-Dist: arrow ==1.3.0
Requires-Dist: asttokens ==2.4.1
Requires-Dist: async-lru ==2.0.4
Requires-Dist: attrs ==23.2.0
Requires-Dist: Babel ==2.14.0
Requires-Dist: beautifulsoup4 ==4.12.2
Requires-Dist: bleach ==6.1.0
Requires-Dist: build ==0.10.0
Requires-Dist: CacheControl ==0.12.14
Requires-Dist: certifi ==2023.11.17
Requires-Dist: cffi ==1.16.0
Requires-Dist: charset-normalizer ==3.3.2
Requires-Dist: cleo ==2.0.1
Requires-Dist: click ==8.1.7
Requires-Dist: comm ==0.2.0
Requires-Dist: contourpy ==1.2.0
Requires-Dist: correction-helper ==2023.6
Requires-Dist: crashtest ==0.4.1
Requires-Dist: cycler ==0.12.1
Requires-Dist: debugpy ==1.8.0
Requires-Dist: decorator ==5.1.1
Requires-Dist: defusedxml ==0.7.1
Requires-Dist: distlib ==0.3.6
Requires-Dist: docutils ==0.18.1
Requires-Dist: dulwich ==0.21.5
Requires-Dist: Engr131-Winter-2022 ==0.0.7
Requires-Dist: exceptiongroup ==1.2.0
Requires-Dist: executing ==2.0.1
Requires-Dist: fastjsonschema ==2.19.1
Requires-Dist: filelock ==3.13.1
Requires-Dist: fonttools ==4.47.0
Requires-Dist: fqdn ==1.5.1
Requires-Dist: friendly ==0.7.21
Requires-Dist: friendly-styles ==0.2
Requires-Dist: friendly-traceback ==0.7.61
Requires-Dist: fsspec ==2023.12.2
Requires-Dist: greenlet ==3.0.3
Requires-Dist: html5lib ==1.1
Requires-Dist: idna ==3.6
Requires-Dist: imagesize ==1.4.1
Requires-Dist: importlib-metadata ==7.0.1
Requires-Dist: installer ==0.7.0
Requires-Dist: ipykernel ==6.28.0
Requires-Dist: ipython ==8.19.0
Requires-Dist: ipywidgets ==8.1.1
Requires-Dist: isoduration ==20.11.0
Requires-Dist: jaraco.classes ==3.2.3
Requires-Dist: jedi ==0.19.1
Requires-Dist: jeepney ==0.8.0
Requires-Dist: Jinja2 ==3.1.2
Requires-Dist: joblib ==1.3.2
Requires-Dist: json5 ==0.9.14
Requires-Dist: jsonpointer ==2.4
Requires-Dist: jsonschema ==4.20.0
Requires-Dist: jsonschema-specifications ==2023.12.1
Requires-Dist: jupyter ==1.0.0
Requires-Dist: jupyter-book ==0.15.1
Requires-Dist: jupyter-cache ==0.6.1
Requires-Dist: jupyter-console ==6.6.3
Requires-Dist: jupyter-events ==0.9.0
Requires-Dist: jupyter-lsp ==2.2.1
Requires-Dist: jupyter-client ==8.6.0
Requires-Dist: jupyter-core ==5.5.1
Requires-Dist: jupyter-server ==2.12.1
Requires-Dist: jupyter-server-terminals ==0.5.1
Requires-Dist: jupyterlab ==4.0.10
Requires-Dist: jupyterlab-widgets ==3.0.9
Requires-Dist: jupyterlab-pygments ==0.3.0
Requires-Dist: jupyterlab-server ==2.25.2
Requires-Dist: keyring ==23.13.1
Requires-Dist: kiwisolver ==1.4.5
Requires-Dist: latexcodec ==2.0.1
Requires-Dist: linkify-it-py ==2.0.2
Requires-Dist: lockfile ==0.12.2
Requires-Dist: markdown-it-py ==2.2.0
Requires-Dist: MarkupSafe ==2.1.3
Requires-Dist: matplotlib ==3.8.2
Requires-Dist: matplotlib-inline ==0.1.6
Requires-Dist: mdit-py-plugins ==0.3.5
Requires-Dist: mdurl ==0.1.2
Requires-Dist: mistune ==3.0.2
Requires-Dist: more-itertools ==9.1.0
Requires-Dist: mpmath ==1.3.0
Requires-Dist: myst-nb ==0.17.2
Requires-Dist: myst-parser ==0.18.1
Requires-Dist: nbclient ==0.7.4
Requires-Dist: nbconvert ==7.13.1
Requires-Dist: nbformat ==5.9.2
Requires-Dist: nest-asyncio ==1.5.8
Requires-Dist: networkx ==3.2.1
Requires-Dist: notebook ==7.0.6
Requires-Dist: notebook-shim ==0.2.3
Requires-Dist: numpy ==1.26.2
Requires-Dist: overrides ==7.4.0
Requires-Dist: packaging ==23.2
Requires-Dist: pandas ==2.1.4
Requires-Dist: pandocfilters ==1.5.0
Requires-Dist: parso ==0.8.3
Requires-Dist: pexpect ==4.9.0
Requires-Dist: Pillow ==10.1.0
Requires-Dist: pkginfo ==1.9.6
Requires-Dist: platformdirs >3.0.0
Requires-Dist: poetry ==1.5.1
Requires-Dist: poetry-core ==1.6.1
Requires-Dist: poetry-plugin-export ==1.4.0
Requires-Dist: prometheus-client ==0.19.0
Requires-Dist: prompt-toolkit ==3.0.43
Requires-Dist: psutil ==5.9.7
Requires-Dist: ptyprocess ==0.7.0
Requires-Dist: pure-eval ==0.2.2
Requires-Dist: pybtex ==0.24.0
Requires-Dist: pybtex-docutils ==1.0.3
Requires-Dist: pycparser ==2.21
Requires-Dist: pydata-sphinx-theme ==0.14.4
Requires-Dist: Pygments ==2.17.2
Requires-Dist: pyparsing ==3.1.1
Requires-Dist: pyproject-hooks ==1.0.0
Requires-Dist: python-dateutil ==2.8.2
Requires-Dist: python-json-logger ==2.0.7
Requires-Dist: pytz ==2023.3.post1
Requires-Dist: PyYAML ==6.0.1
Requires-Dist: pyzmq ==25.1.2
Requires-Dist: qtconsole ==5.5.1
Requires-Dist: QtPy ==2.4.1
Requires-Dist: rapidfuzz ==2.15.1
Requires-Dist: referencing ==0.32.0
Requires-Dist: requests ==2.31.0
Requires-Dist: requests-toolbelt ==1.0.0
Requires-Dist: rfc3339-validator ==0.1.4
Requires-Dist: rfc3986-validator ==0.1.1
Requires-Dist: rich ==13.7.0
Requires-Dist: rpds-py ==0.16.2
Requires-Dist: scikit-learn ==1.3.2
Requires-Dist: scipy ==1.11.4
Requires-Dist: seaborn ==0.13.0
Requires-Dist: SecretStorage ==3.3.3
Requires-Dist: Send2Trash ==1.8.2
Requires-Dist: shapely ==2.0.1
Requires-Dist: shellingham ==1.5.0.post1
Requires-Dist: six ==1.16.0
Requires-Dist: sniffio ==1.3.0
Requires-Dist: snowballstemmer ==2.2.0
Requires-Dist: soupsieve ==2.5
Requires-Dist: Sphinx ==5.0.2
Requires-Dist: sphinx-book-theme ==1.0.1
Requires-Dist: sphinx-comments ==0.0.3
Requires-Dist: sphinx-copybutton ==0.5.2
Requires-Dist: sphinx-jupyterbook-latex ==0.5.2
Requires-Dist: sphinx-multitoc-numbering ==0.1.3
Requires-Dist: sphinx-thebe ==0.2.1
Requires-Dist: sphinx-togglebutton ==0.3.2
Requires-Dist: sphinx-design ==0.3.0
Requires-Dist: sphinx-external-toc ==0.3.1
Requires-Dist: sphinxcontrib-applehelp ==1.0.7
Requires-Dist: sphinxcontrib-bibtex ==2.5.0
Requires-Dist: sphinxcontrib-devhelp ==1.0.5
Requires-Dist: sphinxcontrib-htmlhelp ==2.0.4
Requires-Dist: sphinxcontrib-jsmath ==1.0.1
Requires-Dist: sphinxcontrib-qthelp ==1.0.6
Requires-Dist: sphinxcontrib-serializinghtml ==1.1.9
Requires-Dist: SQLAlchemy ==2.0.24
Requires-Dist: stack-data ==0.6.3
Requires-Dist: sympy ==1.12
Requires-Dist: tabulate ==0.9.0
Requires-Dist: terminado ==0.18.0
Requires-Dist: terminaltables ==3.1.10
Requires-Dist: threadpoolctl ==3.2.0
Requires-Dist: tinycss2 ==1.2.1
Requires-Dist: tomli ==2.0.1
Requires-Dist: tomlkit ==0.11.8
Requires-Dist: torch ==2.1.2
Requires-Dist: torchsummary ==1.5.1
Requires-Dist: tornado ==6.4
Requires-Dist: traitlets ==5.14.0
Requires-Dist: trove-classifiers ==2023.5.24
Requires-Dist: types-python-dateutil ==2.8.19.14
Requires-Dist: typing-extensions ==4.9.0
Requires-Dist: tzdata ==2023.4
Requires-Dist: uc-micro-py ==1.0.2
Requires-Dist: uri-template ==1.3.0
Requires-Dist: urllib3 ==1.26.18
Requires-Dist: virtualenv ==20.23.1
Requires-Dist: wcwidth ==0.2.12
Requires-Dist: webcolors ==1.13
Requires-Dist: webencodings ==0.5.1
Requires-Dist: websocket-client ==1.7.0
Requires-Dist: widgetsnbextension ==4.0.9
Requires-Dist: zipp ==3.17.0
Requires-Dist: scikit-image ==0.22.0
Requires-Dist: otter-grader ==5.2.2
Requires-Dist: nbgitpuller
Requires-Dist: drexel-jupyter-logger
Requires-Dist: ENGR131-Util-2024
